graiax/fastapi/__init__.py
graiax/fastapi/interface.py
graiax/fastapi/py.typed
graiax/fastapi/saya/__init__.py
graiax/fastapi/saya/behaviour.py
graiax/fastapi/saya/route.py
graiax/fastapi/saya/schema.py
graiax/fastapi/service.py
graiax_fastapi-0.4.1.dist-info/METADATA
graiax_fastapi-0.4.1.dist-info/WHEEL
graiax_fastapi-0.4.1.dist-info/licenses/LICENSE
graiax_fastapi-0.4.1.dist-info/RECORD
