Metadata-Version: 2.1
Name: graiax-fastapi
Version: 0.4.1
Summary: FastAPI launcher for GraiaCommunity.
Author-Email: BlueGlassBlock <blueglassblock@outlook.com>, Red_lnn <w731347477@gmail.com>
License: MIT
Classifier: Typing :: Typed
Classifier: Development Status :: 4 - Beta
Classifier: Programming Language :: Python :: 3
Classifier: Programming Language :: Python :: 3.9
Classifier: Programming Language :: Python :: 3.10
Classifier: Programming Language :: Python :: 3.11
Project-URL: Repository, https://github.com/GraiaCommunity/graiax-fastapi
Requires-Python: >=3.9
Requires-Dist: fastapi>=0.101.0
Requires-Dist: graia-amnesia>=0.8.2
Requires-Dist: graia-saya>=0.0.18
Requires-Dist: launart>=0.8.1
